setup.py
fanscript/fan_script.py
ventprogramm.egg-info/PKG-INFO
ventprogramm.egg-info/SOURCES.txt
ventprogramm.egg-info/dependency_links.txt
ventprogramm.egg-info/top_level.txt